itly_sdk/__init__.py
itly_sdk/_environment.py
itly_sdk/_event.py
itly_sdk/_itly.py
itly_sdk/_logger.py
itly_sdk/_options.py
itly_sdk/_plugin.py
itly_sdk/_plugin_options.py
itly_sdk/_properties.py
itly_sdk/_validation_options.py
itly_sdk/_validation_response.py
itly_sdk/internal/__init__.py
itly_sdk/internal/_async_consumer.py
itly_sdk/internal/_backoff.py
itly_sdk-0.1.24.dist-info/WHEEL
itly_sdk-0.1.24.dist-info/METADATA
itly_sdk-0.1.24.dist-info/RECORD
